lsp_client/__init__.py
lsp_client/capability/__init__.py
lsp_client/capability/build.py
lsp_client/capability/diagnostic/__init__.py
lsp_client/capability/diagnostic/document.py
lsp_client/capability/diagnostic/workspace.py
lsp_client/capability/notification/__init__.py
lsp_client/capability/notification/did_change_configuration.py
lsp_client/capability/notification/did_change_workspace_folders.py
lsp_client/capability/notification/did_create_files.py
lsp_client/capability/notification/did_delete_files.py
lsp_client/capability/notification/did_rename_files.py
lsp_client/capability/notification/text_document_synchronize.py
lsp_client/capability/request/__init__.py
lsp_client/capability/request/call_hierarchy.py
lsp_client/capability/request/code_action.py
lsp_client/capability/request/completion.py
lsp_client/capability/request/declaration.py
lsp_client/capability/request/definition.py
lsp_client/capability/request/document_symbol.py
lsp_client/capability/request/hover.py
lsp_client/capability/request/implementation.py
lsp_client/capability/request/inlay_hint.py
lsp_client/capability/request/inline_value.py
lsp_client/capability/request/reference.py
lsp_client/capability/request/rename.py
lsp_client/capability/request/signature_help.py
lsp_client/capability/request/type_definition.py
lsp_client/capability/request/type_hierarchy.py
lsp_client/capability/request/will_create_files.py
lsp_client/capability/request/will_delete_files.py
lsp_client/capability/request/will_rename_files.py
lsp_client/capability/request/workspace_edit.py
lsp_client/capability/request/workspace_symbol.py
lsp_client/capability/server_notification/__init__.py
lsp_client/capability/server_notification/log_message.py
lsp_client/capability/server_notification/log_trace.py
lsp_client/capability/server_notification/publish_diagnostics.py
lsp_client/capability/server_notification/show_message.py
lsp_client/capability/server_request/__init__.py
lsp_client/capability/server_request/apply_edit.py
lsp_client-0.3.3.dist-info/WHEEL
lsp_client-0.3.3.dist-info/METADATA
lsp_client-0.3.3.dist-info/RECORD
