Metadata-Version: 2.3
Name: lsp-client
Version: 0.3.3
Summary: Full-featured, well-typed, and easy-to-use LSP client
Keywords: Language Server Protocol,LSP
Author: observerw
Author-email: observerw <wozluohd@gmail.com>
Classifier: Programming Language :: Python
Classifier: Programming Language :: Python :: 3.12
Classifier: License :: OSI Approved :: MIT License
Requires-Dist: aioshutil>=1.6
Requires-Dist: anyio>=4.10.0
Requires-Dist: asyncer>=0.0.10
Requires-Dist: attrs>=25.3.0
Requires-Dist: loguru>=0.7.3
Requires-Dist: lsprotocol>=2025.0.0
Requires-Dist: pydantic-settings>=2.12.0
Requires-Dist: semver>=3.0.4
Requires-Dist: tenacity>=9.1.2
Requires-Dist: xxhash>=3.6.0
Requires-Python: >=3.12
